{
  "logo": "Del Be Del · دل به دل",
  "nav.dashboard": "Dashboard",
  "nav.profile": "Profile",
  "nav.logout": "Logout",
  "nav.login": "Login",
  "nav.register": "Register",
  "nav.language": "فا",

  "hero.title": "Del Be Del",
  "hero.subtitle": "Heart to Heart",
  "hero.description": "A research platform exploring the hidden rhythms of human connection. Add the people you care about, tap when they cross your mind, and discover whether your thoughts align — without ever being told in real time.",
  "hero.getStarted": "Get Started",
  "hero.login": "Login",

  "intro.title": "How It Works",
  "intro.step1.title": "Create Your Account",
  "intro.step1.desc": "Sign up with a unique username that your connections will use to find you.",
  "intro.step2.title": "Add Connections",
  "intro.step2.desc": "Search for people by username and add them to your circle.",
  "intro.step3.title": "Tap When You Think of Them",
  "intro.step3.desc": "A simple heart tap records the moment — no notification is sent.",
  "intro.step4.title": "Discover at 11 PM",
  "intro.step4.desc": "Each night, see a summary of who thought about you in the past 7 days.",

  "register.title": "Create an Account",
  "register.displayName": "Display Name",
  "register.username": "Username",
  "register.usernamePlaceholder": "3–20 chars, lowercase letters, numbers, underscores",
  "register.email": "Email",
  "register.password": "Password",
  "register.submit": "Register",
  "register.creating": "Creating account...",
  "register.hasAccount": "Already have an account?",
  "register.loginLink": "Login",
  "register.usernameTaken": "This username is already taken.",
  "register.usernameInvalid": "Username must be 3–20 characters: lowercase letters, numbers, or underscores.",

  "login.title": "Welcome Back",
  "login.email": "Email",
  "login.password": "Password",
  "login.submit": "Login",
  "login.loggingIn": "Logging in...",
  "login.noAccount": "Don't have an account?",
  "login.registerLink": "Register",

  "dash.greeting": "Welcome, {name}",
  "dash.subtitle": "Your connections and activity appear here.",
  "dash.guide.title": "Getting Started",
  "dash.guide.step1": "Go to your Profile to see your username.",
  "dash.guide.step2": "Share your username with people you want to connect with.",
  "dash.guide.step3": "Search for others by username to add them as connections.",
  "dash.guide.step4": "Tap the heart whenever someone crosses your mind.",
  "dash.guide.step5": "Check back at 11 PM to see your daily summary.",
  "dash.guide.dismiss": "Got it",

  "dash.search.placeholder": "Search by username...",
  "dash.search.btn": "Add",
  "dash.search.notFound": "No user found with that username.",
  "dash.search.alreadyAdded": "You already have this connection.",
  "dash.search.selfAdd": "You cannot add yourself.",
  "dash.search.added": "Connection added!",
  "dash.search.searching": "Searching...",

  "dash.connections.title": "Your Connections",
  "dash.connections.empty": "No connections yet. Search for a username above to add someone.",
  "dash.connections.remove": "Remove",
  "dash.connections.removeConfirm": "Remove {name} from your connections?",
  "dash.connections.tappedToday": "You tapped {name} {count} time(s) today",
  "dash.connections.cooldown": "Wait a moment before tapping again",

  "dash.summary.title": "Your Summary",
  "dash.summary.last24h": "Last 24 hours",
  "dash.summary.last7d": "Last 7 days",
  "dash.summary.updatesAt": "Updates at 11 PM",
  "dash.summary.noTaps": "No one has tapped you yet.",
  "dash.summary.taps24h": "{name} — {count} tap(s)",
  "dash.summary.taps7d": "{name} — {count} tap(s)",

  "tap.sent": "Sent",

  "profile.title": "Your Profile",
  "profile.email": "Email",
  "profile.username": "Username",
  "profile.uid": "User ID",
  "profile.joined": "Joined",
  "profile.displayName": "Display Name",
  "profile.save": "Save Changes",
  "profile.saving": "Saving...",
  "profile.updated": "Profile updated."
}
